<?xml version="1.0" encoding="utf-8"?>
<odoo>
    <data>

        <record id="l10n_sa.sa_withholding_tax_5_rental" model="account.tax.template">
            <field name="l10n_sa_is_retention" eval="True"/>
        </record>
        <record id="l10n_sa.sa_withholding_tax_5_tickets_or_air_freight" model="account.tax.template">
            <field name="l10n_sa_is_retention" eval="True"/>
        </record>
        <record id="l10n_sa.sa_withholding_tax_5_tickets_or_sea_freight" model="account.tax.template">
            <field name="l10n_sa_is_retention" eval="True"/>
        </record>
        <record id="l10n_sa.sa_withholding_tax_5_international_telecommunication" model="account.tax.template">
            <field name="l10n_sa_is_retention" eval="True"/>
        </record>
        <record id="l10n_sa.sa_withholding_tax_5_distributed_profits" model="account.tax.template">
            <field name="l10n_sa_is_retention" eval="True"/>
        </record>
        <record id="l10n_sa.sa_withholding_tax_5_consulting_and_technical" model="account.tax.template">
            <field name="l10n_sa_is_retention" eval="True"/>
        </record>
        <record id="l10n_sa.sa_withholding_tax_5_return_from_loans" model="account.tax.template">
            <field name="l10n_sa_is_retention" eval="True"/>
        </record>
        <record id="l10n_sa.sa_withholding_tax_5_insurance_amd_reinsurance" model="account.tax.template">
            <field name="l10n_sa_is_retention" eval="True"/>
        </record>
        <record id="l10n_sa.sa_withholding_tax_15_royalties" model="account.tax.template">
            <field name="l10n_sa_is_retention" eval="True"/>
        </record>
        <record id="l10n_sa.sa_withholding_tax_15_paid_services_from_main_branch" model="account.tax.template">
            <field name="l10n_sa_is_retention" eval="True"/>
        </record>
        <record id="l10n_sa.sa_withholding_tax_15_paid_services_from_another_branch" model="account.tax.template">
            <field name="l10n_sa_is_retention" eval="True"/>
        </record>
        <record id="l10n_sa.sa_withholding_tax_15_others" model="account.tax.template">
            <field name="l10n_sa_is_retention" eval="True"/>
        </record>
        <record id="l10n_sa.sa_withholding_tax_20_managerial" model="account.tax.template">
            <field name="l10n_sa_is_retention" eval="True"/>
        </record>

    </data>
</odoo>