<?xml version="1.0" encoding="utf-8"?>
<odoo>
    <record id="view_l10n_in_account_journal_form_inherit_new" model="ir.ui.view">
        <field name="name">l10n.in.account.journal.form.inherit</field>
        <field name="model">account.journal</field>
        <field name="inherit_id" ref="l10n_in.view_account_journal_form_inherit_l10n_in"/>
        <field name="arch" type="xml">
            <xpath expr="//field[@name='l10n_in_gstin_partner_id']" position="attributes">
                <attribute name="string">GST IN Unit</attribute>
            </xpath>
        </field>
    </record>
</odoo>
