<?xml version="1.0" encoding="UTF-8"?>
<odoo>

    <record id="res_config_settings_view_form" model="ir.ui.view">
        <field name="name">res.config.settings.view.form.inherit.sale.pdf.quote.builder</field>
        <field name="model">res.config.settings</field>
        <field name="inherit_id" ref="sale_management.res_config_settings_view_form"/>
        <field name="arch" type="xml">
            <setting id="sale_pdf_quote_builder" position="inside">
                <div class="mt16">
                    <label for="sale_header" class="me-2"/>
                    <field name="sale_header"/>
<!--                    TODO edm: find where to modify framework JS to show the file's name instead -->
                </div>
                <div class="mt16">
                    <label for="sale_footer" class="me-2"/>
                    <field name="sale_footer"/>
                </div>
            </setting>
        </field>
    </record>

</odoo>
